GoRumenZhinan/README.md
GoRumenZhinan/__init__.py
GoRumenZhinan/__main__.py
GoRumenZhinan/file.epub
GoRumenZhinan/index.html
GoRumenZhinan/css/__init__.py
GoRumenZhinan/css/annotations.css
GoRumenZhinan/css/main.css
GoRumenZhinan/css/normalize.css
GoRumenZhinan/css/popup.css
GoRumenZhinan/font/__init__.py
GoRumenZhinan/font/fontello.eot
GoRumenZhinan/font/fontello.svg
GoRumenZhinan/font/fontello.ttf
GoRumenZhinan/font/fontello.woff
GoRumenZhinan/img/__init__.py
GoRumenZhinan/img/annotator-glyph-sprite.png
GoRumenZhinan/img/annotator-icon-sprite.png
GoRumenZhinan/img/apple-touch-icon.png
GoRumenZhinan/img/cancelfullscreen.png
GoRumenZhinan/img/close.png
GoRumenZhinan/img/fullscreen.png
GoRumenZhinan/img/loader.gif
GoRumenZhinan/img/menu-icon.png
GoRumenZhinan/img/save.png
GoRumenZhinan/img/saved.png
GoRumenZhinan/img/settings-s.png
GoRumenZhinan/img/settings.png
GoRumenZhinan/img/star.png
GoRumenZhinan/js/__init__.py
GoRumenZhinan/js/epub.js
GoRumenZhinan/js/epub.min.js
GoRumenZhinan/js/epub.min.map
GoRumenZhinan/js/hooks.min.js
GoRumenZhinan/js/hooks.min.map
GoRumenZhinan/js/reader.js
GoRumenZhinan/js/reader.js.map
GoRumenZhinan/js/reader.min.js
GoRumenZhinan/js/reader.min.map
GoRumenZhinan/js/hooks/__init__.py
GoRumenZhinan/js/hooks/extensions/__init__.py
GoRumenZhinan/js/hooks/extensions/highlight.js
GoRumenZhinan/js/libs/__init__.py
GoRumenZhinan/js/libs/jquery.min.js
GoRumenZhinan/js/libs/localforage.min.js
GoRumenZhinan/js/libs/screenfull.js
GoRumenZhinan/js/libs/screenfull.min.js
GoRumenZhinan/js/libs/zip.min.js
GoRumenZhinan/js/plugins/__init__.py
GoRumenZhinan/js/plugins/hypothesis.js
GoRumenZhinan/js/plugins/search.js
go_rumen_zhinan-2024.3.1.0.dist-info/METADATA
go_rumen_zhinan-2024.3.1.0.dist-info/WHEEL
go_rumen_zhinan-2024.3.1.0.dist-info/entry_points.txt
go_rumen_zhinan-2024.3.1.0.dist-info/top_level.txt
go_rumen_zhinan-2024.3.1.0.dist-info/RECORD
